tnprofanity/__init__.py
tnprofanity/thai_profane_wordlist.txt
tnprofanity/thai_white_wordlist.txt
tnprofanity/tnprofanity.py
tnprofanity/tnprofanity.pyc
tnprofanity-0.4.1.dist-info/METADATA
tnprofanity-0.4.1.dist-info/WHEEL
tnprofanity-0.4.1.dist-info/top_level.txt
tnprofanity-0.4.1.dist-info/RECORD
