Metadata-Version: 2.1
Name: tnprofanity
Version: 0.4.1
Summary: thai-text profanity library
Home-page: UNKNOWN
Author: GarKoZ
Author-email: gark36@gmail.com
License: MIT
Keywords: thai english profanity censor
Platform: UNKNOWN
